balex/__init__.py
balex/client.py
balex/exceptions.py
balex/logger.py
balex/examples/send_message.py
balex/examples/webhook_example.py
balex-1.3.0.dist-info/METADATA
balex-1.3.0.dist-info/WHEEL
balex-1.3.0.dist-info/top_level.txt
balex-1.3.0.dist-info/RECORD
