Metadata-Version: 2.4
Name: balex
Version: 1.3.0
Summary: Python library Bale Messenger
Author: z8r-service
Requires-Python: >=3.9
Requires-Dist: aiohttp
